bun/__init__.py
bun/base.py
bun/cli.py
bun/ui.py
bun-0.0.8.dist-info/LICENSE
bun-0.0.8.dist-info/METADATA
bun-0.0.8.dist-info/WHEEL
bun-0.0.8.dist-info/top_level.txt
bun-0.0.8.dist-info/RECORD
