Metadata-Version: 2.1
Name: bun
Version: 0.0.8
Summary: A Python package for a basic CLI and GUI user interface
Home-page: https://github.com/caltechlibrary/bun
Author: Michael Hucka
Author-email: mhucka@caltech.edu
License: BSD 3-clause
Project-URL: Source Code, https://github.com/caltechlibrary/bun
Project-URL: Bug Tracker, https://github.com/caltechlibrary/bun/issues
Keywords: Python,utilities,CLI,GUI,user interfaces
Platform: UNKNOWN
Classifier: Development Status :: 4 - Beta
Classifier: License :: OSI Approved :: BSD License
Classifier: Intended Audience :: Science/Research
Classifier: Operating System :: MacOS :: MacOS X
Classifier: Operating System :: Microsoft :: Windows
Classifier: Operating System :: POSIX
Classifier: Operating System :: POSIX :: Linux
Classifier: Operating System :: Unix
Classifier: Programming Language :: Python
Classifier: Programming Language :: Python :: 3.6
Classifier: Topic :: Software Development :: User Interfaces
Requires-Python: >=3.6
License-File: LICENSE
